MANIFEST.in
README.md
setup.cfg
setup.py
apache_flink_ml.egg-info/PKG-INFO
apache_flink_ml.egg-info/SOURCES.txt
apache_flink_ml.egg-info/dependency_links.txt
apache_flink_ml.egg-info/requires.txt
apache_flink_ml.egg-info/top_level.txt
deps/examples/ml/__init__.py
deps/examples/ml/arraytovector_example.py
deps/examples/ml/vectortoarray_example.py
deps/examples/ml/classification/__init__.py
deps/examples/ml/classification/knn_example.py
deps/examples/ml/classification/linearsvc_example.py
deps/examples/ml/classification/logisticregression_example.py
deps/examples/ml/classification/naivebayes_example.py
deps/examples/ml/clustering/__init__.py
deps/examples/ml/clustering/agglomerativeclustering_example.py
deps/examples/ml/clustering/kmeans_example.py
deps/examples/ml/evaluation/__init__.py
deps/examples/ml/evaluation/binaryclassificationevaluator_example.py
deps/examples/ml/feature/__init__.py
deps/examples/ml/feature/binarizer_example.py
deps/examples/ml/feature/bucketizer_example.py
deps/examples/ml/feature/countvectorizer_example.py
deps/examples/ml/feature/dct_example.py
deps/examples/ml/feature/elementwiseproduct_example.py
deps/examples/ml/feature/featurehasher_example.py
deps/examples/ml/feature/hashingtf_example.py
deps/examples/ml/feature/idf_example.py
deps/examples/ml/feature/imputer_example.py
deps/examples/ml/feature/indextostringmodel_example.py
deps/examples/ml/feature/interaction_example.py
deps/examples/ml/feature/kbinsdiscreteizer_example.py
deps/examples/ml/feature/maxabsscaler_example.py
deps/examples/ml/feature/minhashlsh_example.py
deps/examples/ml/feature/minmaxscaler_example.py
deps/examples/ml/feature/ngram_example.py
deps/examples/ml/feature/normalizer_example.py
deps/examples/ml/feature/onehotencoder_example.py
deps/examples/ml/feature/online_standardscaler_example.py
deps/examples/ml/feature/polynomialexpansion_example.py
deps/examples/ml/feature/randomsplitter_example.py
deps/examples/ml/feature/regextokenizer_example.py
deps/examples/ml/feature/robustscaler_example.py
deps/examples/ml/feature/sqltransformer_example.py
deps/examples/ml/feature/standardscaler_example.py
deps/examples/ml/feature/stopwordsremover_example.py
