Metadata-Version: 2.1
Name: apache-flink-ml
Version: 2.3.0
Summary: Apache Flink ML Python API
Home-page: https://flink.apache.org
Author: Apache Software Foundation
Author-email: dev@flink.apache.org
License: https://www.apache.org/licenses/LICENSE-2.0
Platform: UNKNOWN
Classifier: Development Status :: 5 - Production/Stable
Classifier: License :: OSI Approved :: Apache Software License
Classifier: Programming Language :: Python :: 3.7
Classifier: Programming Language :: Python :: 3.8
Requires-Python: >=3.7
